git_history/__init__.py
git_history/cli.py
git_history/utils.py
git_history-0.8.dist-info/licenses/LICENSE
git_history-0.8.dist-info/METADATA
git_history-0.8.dist-info/WHEEL
git_history-0.8.dist-info/entry_points.txt
git_history-0.8.dist-info/top_level.txt
git_history-0.8.dist-info/RECORD
