Metadata-Version: 2.4
Name: git-history
Version: 0.8
Summary: Tools for analyzing Git history using SQLite
Author: Simon Willison
License-Expression: Apache-2.0
Project-URL: Homepage, https://github.com/simonw/git-history
Project-URL: Changelog, https://github.com/simonw/git-history/releases
Project-URL: Issues, https://github.com/simonw/git-history/issues
Project-URL: CI, https://github.com/simonw/git-history/actions
Requires-Python: >=3.10
License-File: LICENSE
Requires-Dist: click
Requires-Dist: GitPython
Requires-Dist: sqlite-utils>=3.19
Dynamic: license-file
